wikihow2zim/VERSION
wikihow2zim/__init__.py
wikihow2zim/__main__.py
wikihow2zim/constants.py
wikihow2zim/entrypoint.py
wikihow2zim/executor.py
wikihow2zim/imager.py
wikihow2zim/rewriter.py
wikihow2zim/scraper.py
wikihow2zim/shared.py
wikihow2zim/utils.py
wikihow2zim/videos.py
wikihow2zim/assets/external-link-ltr-icon.svg
wikihow2zim/assets/external-link-rtl-icon.svg
wikihow2zim/assets/wikihow2zim.css
wikihow2zim/assets/wikihow2zim.js
wikihow2zim/assets/vendor/videojs-ogvjs.js
wikihow2zim/assets/vendor/ogvjs/COPYING
wikihow2zim/assets/vendor/ogvjs/COPYING-dav1d.txt
wikihow2zim/assets/vendor/ogvjs/COPYING-ogg.txt
wikihow2zim/assets/vendor/ogvjs/COPYING-opus.txt
wikihow2zim/assets/vendor/ogvjs/COPYING-theora.txt
wikihow2zim/assets/vendor/ogvjs/COPYING-vorbis.txt
wikihow2zim/assets/vendor/ogvjs/LICENSE-nestegg.txt
wikihow2zim/assets/vendor/ogvjs/LICENSE-vpx.txt
wikihow2zim/assets/vendor/ogvjs/PATENTS-vpx.txt
wikihow2zim/assets/vendor/ogvjs/README.md
wikihow2zim/assets/vendor/ogvjs/ogv-decoder-audio-opus-wasm.js
wikihow2zim/assets/vendor/ogvjs/ogv-decoder-audio-opus-wasm.wasm
wikihow2zim/assets/vendor/ogvjs/ogv-decoder-audio-vorbis-wasm.js
wikihow2zim/assets/vendor/ogvjs/ogv-decoder-audio-vorbis-wasm.wasm
wikihow2zim/assets/vendor/ogvjs/ogv-decoder-video-av1-mt-wasm.js
wikihow2zim/assets/vendor/ogvjs/ogv-decoder-video-av1-mt-wasm.wasm
wikihow2zim/assets/vendor/ogvjs/ogv-decoder-video-av1-mt-wasm.worker.js
wikihow2zim/assets/vendor/ogvjs/ogv-decoder-video-av1-wasm.js
wikihow2zim/assets/vendor/ogvjs/ogv-decoder-video-av1-wasm.wasm
wikihow2zim/assets/vendor/ogvjs/ogv-decoder-video-theora-wasm.js
wikihow2zim/assets/vendor/ogvjs/ogv-decoder-video-theora-wasm.wasm
wikihow2zim/assets/vendor/ogvjs/ogv-decoder-video-vp8-mt-wasm.js
wikihow2zim/assets/vendor/ogvjs/ogv-decoder-video-vp8-mt-wasm.wasm
wikihow2zim/assets/vendor/ogvjs/ogv-decoder-video-vp8-mt-wasm.worker.js
wikihow2zim/assets/vendor/ogvjs/ogv-decoder-video-vp8-wasm.js
wikihow2zim-1.2.3.dist-info/LICENSE
wikihow2zim-1.2.3.dist-info/METADATA
wikihow2zim-1.2.3.dist-info/WHEEL
wikihow2zim-1.2.3.dist-info/entry_points.txt
wikihow2zim-1.2.3.dist-info/top_level.txt
wikihow2zim-1.2.3.dist-info/RECORD
