Metadata-Version: 2.1
Name: wikihow2zim
Version: 1.2.3
Summary: Make ZIM file from WikiHow articles
Home-page: https://kiwix.org/
Author: Kiwix Team
Author-email: dev@kiwix.org
License: GPLv3+
Keywords: kiwix zim offline wikihow
Classifier: Programming Language :: Python
Classifier: Programming Language :: Python :: 3.8
Classifier: License :: OSI Approved :: GNU General Public License v3 or later (GPLv3+)
Requires-Python: >=3.8
License-File: LICENSE
Requires-Dist: requests <3.0,>=2.28.0
Requires-Dist: Jinja2 <4.0,>=3.1.2
Requires-Dist: zimscraperlib <2.1,>=2.0.0
Requires-Dist: cssbeautifier <2.0,>=1.10.3
Requires-Dist: kiwixstorage <0.9,>=0.8.1
Requires-Dist: pif <0.9,>=0.8.2
Requires-Dist: tld <0.13,>=0.12.6
Requires-Dist: pywikiapi ==4.3.0
Requires-Dist: backoff <2.2,>=2.1.2
